earthkit/workflows/plugins/anemoi/__init__.py
earthkit/workflows/plugins/anemoi/_version.py
earthkit/workflows/plugins/anemoi/fluent.py
earthkit/workflows/plugins/anemoi/inference.py
earthkit/workflows/plugins/anemoi/runner.py
earthkit/workflows/plugins/anemoi/types.py
earthkit_workflows_anemoi-0.3.12.dist-info/licenses/LICENSE
earthkit_workflows_anemoi-0.3.12.dist-info/METADATA
earthkit_workflows_anemoi-0.3.12.dist-info/WHEEL
earthkit_workflows_anemoi-0.3.12.dist-info/top_level.txt
earthkit_workflows_anemoi-0.3.12.dist-info/RECORD
