Metadata-Version: 2.4
Name: earthkit-workflows-anemoi
Version: 0.3.12
Summary: An earthkit-workflows interface to anemoi inference
Author-email: "European Centre for Medium-Range Weather Forecasts (ECMWF)" <software.support@ecmwf.int>
License-Expression: Apache-2.0
Classifier: Programming Language :: Python :: 3 :: Only
Classifier: Programming Language :: Python :: 3.10
Classifier: Programming Language :: Python :: 3.11
Classifier: Programming Language :: Python :: 3.12
Classifier: Programming Language :: Python :: 3.13
Requires-Python: >=3.10
License-File: LICENSE
Requires-Dist: anemoi-datasets>=0.5.21
Requires-Dist: anemoi-inference>=0.7
Requires-Dist: earthkit-workflows>=0.4.1
Provides-Extra: docs
Requires-Dist: autodoc-pydantic; extra == "docs"
Requires-Dist: nbsphinx; extra == "docs"
Requires-Dist: pandoc; extra == "docs"
Requires-Dist: rstfmt; extra == "docs"
Requires-Dist: sphinx<8.2; extra == "docs"
Requires-Dist: sphinx-argparse<0.5; extra == "docs"
Requires-Dist: sphinx-rtd-theme; extra == "docs"
Provides-Extra: tests
Requires-Dist: pytest; extra == "tests"
Requires-Dist: pytest-mock; extra == "tests"
Requires-Dist: pytest-xdist; extra == "tests"
Dynamic: license-file
